commander_py/__init__.py
commander_py-2.0.2.dist-info/METADATA
commander_py-2.0.2.dist-info/WHEEL
commander_py-2.0.2.dist-info/LICENSE
commander_py-2.0.2.dist-info/RECORD
