Metadata-Version: 2.1
Name: commander-py
Version: 2.0.2
Summary: A very simple tool to create beautiful console application by using native argparse.
Home-page: https://ozcanyarimdunya.github.io/commander_py/
License: MIT
Keywords: commander,argparse
Author: Özcan Yarımdünya
Author-email: ozcanyd@gmail.com
Requires-Python: >=3.7,<4.0
Classifier: Development Status :: 4 - Beta
Classifier: License :: OSI Approved :: MIT License
Classifier: Operating System :: OS Independent
Classifier: Programming Language :: Python :: 3
Classifier: Programming Language :: Python :: 3.7
Classifier: Programming Language :: Python :: 3.8
Classifier: Programming Language :: Python :: 3.9
Classifier: Programming Language :: Python :: 3.10
Classifier: Programming Language :: Python :: 3.11
Classifier: Programming Language :: Python :: 3
Classifier: Programming Language :: Python :: 3 :: Only
Classifier: Programming Language :: Python :: 3.10
Classifier: Programming Language :: Python :: 3.7
Classifier: Programming Language :: Python :: 3.8
Classifier: Programming Language :: Python :: 3.9
Classifier: Topic :: Software Development :: Libraries
Project-URL: Documentation, https://ozcanyarimdunya.github.io/commander_py/
Project-URL: Repository, https://github.com/ozcanyarimdunya/commander_py
